pyeng/__init__.py
pyeng/general/__init__.py
pyeng/general/validation.py
pyeng/general/beams/__init__.py
pyeng/general/beams/deflection.py
pyeng/general/geometry/__init__.py
pyeng/general/geometry/geom_2d.py
pyeng/geotechnical/__init__.py
pyeng/geotechnical/classification/__init__.py
pyeng/geotechnical/classification/index_tests.py
pyeng/geotechnical/consolidation/__init__.py
pyeng/geotechnical/consolidation/onedimensional.py
pyeng/geotechnical/correlations/__init__.py
pyeng/geotechnical/correlations/clay.py
pyeng/geotechnical/correlations/sand.py
pyeng/geotechnical/shallow_foundations/__init__.py
pyeng/geotechnical/shallow_foundations/capacity.py
pyeng/geotechnical/stress_strain/__init__.py
pyeng/geotechnical/stress_strain/elastic.py
pyeng/hydraulics/__init__.py
pyeng/hydraulics/basics/__init__.py
pyeng/hydraulics/basics/dimensionless_numbers.py
pyeng/hydraulics/pipe_flow/__init__.py
pyeng/hydraulics/pipe_flow/pressure_calcs.py
tests/__init__.py
tests/general/__init__.py
tests/general/test_validation.py
tests/general/beams/__init__.py
tests/general/beams/test_deflection.py
tests/general/geometry/__init__.py
tests/general/geometry/test_geom_2d.py
tests/geotechnical/__init__.py
tests/geotechnical/classification/__init__.py
tests/geotechnical/classification/test_index_tests.py
tests/geotechnical/consolidation/__init__.py
tests/geotechnical/consolidation/test_onedimensional.py
tests/geotechnical/correlations/__init__.py
tests/geotechnical/correlations/test_clay.py
tests/geotechnical/correlations/test_sand.py
tests/geotechnical/shallow_foundations/__init__.py
tests/geotechnical/shallow_foundations/test_capacity.py
tests/geotechnical/stress_strain/__init__.py
tests/geotechnical/stress_strain/test_elastic.py
tests/hydraulics/__init__.py
tests/hydraulics/pipe_flow/__init__.py
tests/hydraulics/pipe_flow/test_pressure_calcs.py
python_engineering-0.0.3.dist-info/LICENSE.txt
python_engineering-0.0.3.dist-info/METADATA
python_engineering-0.0.3.dist-info/WHEEL
python_engineering-0.0.3.dist-info/top_level.txt
python_engineering-0.0.3.dist-info/RECORD
