Metadata-Version: 2.1
Name: python-engineering
Version: 0.0.3
Summary: python-engineering, the ultimate engineering function library
Home-page: https://github.com/snakesonabrain/python-engineering
Download-URL: https://github.com/snakesonabrain/python-engineering/archive/master.zip
Author: Bruno Stuyts
Author-email: bruno@pro-found.be
License: Creative Commons BY-SA 4.0
Keywords: engineering,geotechnical,mechanical
License-File: LICENSE.txt
